rabbitmq_integration/__init__.py
rabbitmq_integration/rabbitmq_api.py
rabbitmq_integration/rabbitmq_commands.py
rabbitmq_integration/rabbitmq_conn.py
django_rabbitmq_utils-0.0.1.dist-info/METADATA
django_rabbitmq_utils-0.0.1.dist-info/WHEEL
django_rabbitmq_utils-0.0.1.dist-info/top_level.txt
django_rabbitmq_utils-0.0.1.dist-info/RECORD
