Metadata-Version: 2.1
Name: django-rabbitmq-utils
Version: 0.0.1
Summary: Enhance RabbitMQ services for a Python Django application
Home-page: https://github.com/Soniyasharma6868/django_rabbitmq_utils
Author: Soniya Sharma
Author-email: sharmasoniya6868@email.com
License: MIT
Project-URL: Source, https://github.com/Soniyasharma6868/django_rabbitmq_utils
Platform: UNKNOWN
Classifier: Intended Audience :: Developers
Classifier: Topic :: Utilities
Classifier: License :: OSI Approved :: MIT License
Classifier: Programming Language :: Python :: 3
Requires-Python: >=3
Requires-Dist: Django
Requires-Dist: kombu
Requires-Dist: pika
Requires-Dist: requests
